rsgis/__init__.py
rsgis/landsat.py
rsgis/main.py
rsgis/metadata.py
tests/__init__.py
tests/metadata_test.py
rsgis-0.0.3.dist-info/LICENSE
rsgis-0.0.3.dist-info/METADATA
rsgis-0.0.3.dist-info/WHEEL
rsgis-0.0.3.dist-info/top_level.txt
rsgis-0.0.3.dist-info/RECORD
