Metadata-Version: 2.1
Name: rsgis
Version: 0.0.3
Summary: A python package for basic to advanced GIS operations
Home-page: https://github.com/jeafreezy/rsgis
Author: Emmanuel Jolaiya
Author-email: jolaiyaemmanuel@gmail.com
License: UNKNOWN
Platform: UNKNOWN
Classifier: Programming Language :: Python :: 3
Classifier: License :: OSI Approved :: MIT License
Classifier: Operating System :: OS Independent
Requires-Python: >=3.6
